db/__init__.py
db/db_connect.py
db/db_operations.py
dir/__init__.py
dir/dir_management.py
font/__init__.py
font/font_setting.py
gui/__init__.py
gui/choice_operations.py
gui/grid_operations.py
mschoi_gui-1.2.2.dist-info/METADATA
mschoi_gui-1.2.2.dist-info/WHEEL
mschoi_gui-1.2.2.dist-info/top_level.txt
mschoi_gui-1.2.2.dist-info/RECORD
